p360_connector_sdk/__init__.py
p360_connector_sdk/api/__init__.py
p360_connector_sdk/api/p360_query_api_base.py
p360_connector_sdk/models/__init__.py
p360_connector_sdk/models/external_response.py
p360_connector_sdk/models/query_ack_response.py
p360_connector_sdk/models/query_request.py
p360_connector_sdk/models/query_response.py
p360_connector_sdk/models/query_result.py
p360_connector_sdk/models/status.py
p360_connector_sdk/utils/__init__.py
p360_connector_sdk/utils/curl_utils.py
p360_connector_sdk-0.2.0.dist-info/METADATA
p360_connector_sdk-0.2.0.dist-info/WHEEL
p360_connector_sdk-0.2.0.dist-info/top_level.txt
p360_connector_sdk-0.2.0.dist-info/RECORD
